evaluateqa/__init__.py
evaluateqa/mintaka/__init__.py
evaluateqa/mintaka/evaluate.py
evaluateqa-0.1.3.dist-info/LICENSE
evaluateqa-0.1.3.dist-info/METADATA
evaluateqa-0.1.3.dist-info/WHEEL
evaluateqa-0.1.3.dist-info/RECORD
