Metadata-Version: 2.1
Name: evaluateqa
Version: 0.1.3
Summary: 
Home-page: https://github.com/MihailSalnikov/EvaluateQA
License: MIT
Keywords: QA,KGQA,ODQA,Evaluate
Author: Mikhail Salnikov
Author-email: 2613180+MihailSalnikov@users.noreply.github.com
Requires-Python: >=3.8,<4.0
Classifier: License :: OSI Approved :: MIT License
Classifier: Programming Language :: Python :: 3
Classifier: Programming Language :: Python :: 3.8
Classifier: Programming Language :: Python :: 3.9
Classifier: Programming Language :: Python :: 3.10
Classifier: Programming Language :: Python :: 3.11
Requires-Dist: joblib (>=1.2.0,<2.0.0)
Requires-Dist: pandas (>=2.0.1,<3.0.0)
Requires-Dist: regex (>=2023.6.3,<2024.0.0)
Requires-Dist: ujson (>=5.7.0,<6.0.0)
Project-URL: Repository, https://github.com/MihailSalnikov/EvaluateQA
